{
	"name": "Eventos VPN",
	"events": [
		{
			"eventType": "block",
			"conditions": [
				{
					"id": "on-object-clicked",
					"objectClass": "Mouse",
					"sid": 124844861203364,
					"parameters": {
						"mouse-button": "left",
						"click-type": "clicked",
						"object-clicked": "Cerrar"
					}
				}
			],
			"actions": [
				{
					"id": "go-to-layout",
					"objectClass": "System",
					"sid": 608299081842754,
					"parameters": {
						"layout": "LaberintoVPN"
					}
				}
			],
			"sid": 903108250376742
		}
	],
	"sid": 206549460786026
}